tar_progress/__init__.py
tar_progress/__main__.py
tar_progress/classes/__init__.py
tar_progress/classes/interface.py
tar_progress/classes/linux.py
tar_progress/classes/windows.py
tar_progress-1.3.3.dist-info/METADATA
tar_progress-1.3.3.dist-info/WHEEL
tar_progress-1.3.3.dist-info/entry_points.txt
tar_progress-1.3.3.dist-info/top_level.txt
tar_progress-1.3.3.dist-info/RECORD
