Metadata-Version: 2.1
Name: tar-progress
Version: 1.3.3
Summary: This utility offer a progress-bar to the GNU tar program, and provide it on Windows
Home-page: https://github.com/henri9813/tar-progress
Author: Henri Devigne
Author-email: henri.devigne@bonkgaming.fr
License: UNKNOWN
Platform: UNKNOWN
Requires-Dist: tqdm
Requires-Dist: enum34
